zeroloader/__init__.py
zeroloader/drive.py
zeroloader/load.py
zeroloader.py-1.0.0.dist-info/LICENSE.md
zeroloader.py-1.0.0.dist-info/METADATA
zeroloader.py-1.0.0.dist-info/WHEEL
zeroloader.py-1.0.0.dist-info/top_level.txt
zeroloader.py-1.0.0.dist-info/RECORD
