Metadata-Version: 2.1
Name: zeroloader.py
Version: 1.0.0
Summary: A package to read 0archive's data from google drive to csv
Home-page: https://github.com/disinfoRG/ZeroLoader
Author: Andrea Wang
Author-email: ayw255@nyu.edu
License: UNKNOWN
Platform: UNKNOWN
Classifier: Programming Language :: Python :: 3
Classifier: License :: OSI Approved :: MIT License
Classifier: Operating System :: OS Independent
Requires-Python: >=3.6
License-File: LICENSE.md
Requires-Dist: python-dotenv
Requires-Dist: google-api-python-client
Requires-Dist: google-auth
Requires-Dist: google-auth-httplib2
Requires-Dist: google-auth-oauthlib
Requires-Dist: oauth2client
Requires-Dist: pandas
